{
  "configurations": [
    {
      "browse": {
        "databaseFilename": "${default}",
        "limitSymbolsToIncludedHeaders": false
      },
      "includePath": [
        "/opt/ros/noetic/include/**",
        "/home/cire2022/CIRE2022/catkin_ws/src/etapa03/include/**",
        "/home/cire2022/CIRE2022/catkin_ws/src/point_cloud_viewer/include/**",
        "/opt/ros/noetic/share/tmc_julius/include/**",
        "/usr/include/**"
      ],
      "name": "ROS",
      "intelliSenseMode": "gcc-x64",
      "compilerPath": "/usr/bin/gcc",
      "cStandard": "gnu11",
      "cppStandard": "c++14"
    }
  ],
  "version": 4
}